acidoseq/__init__.py
acidoseq/acidoseq.py
acidoseq-1.1.dist-info/METADATA
acidoseq-1.1.dist-info/RECORD
acidoseq-1.1.dist-info/WHEEL
acidoseq-1.1.dist-info/top_level.txt
map/map.py
