Metadata-Version: 2.1
Name: acidoseq
Version: 1.1
Summary: Studying Acidobacteria reads
Home-page: https://github.com/sap218/acidoseq
Author: Samanthe C Pendle
Author-email: samanfapendle@outlook.com
License: MIT
Platform: UNKNOWN
Classifier: Programming Language :: Python :: 3
Classifier: License :: OSI Approved :: MIT License
Classifier: Operating System :: OS Independent
